[{"category":"News _ Politics","count":"12","categoryId":"11","videoId":"6545"},{"category":"News _ Politics","count":"12","categoryId":"11","videoId":"6570"},{"category":"News _ Politics","count":"12","categoryId":"11","videoId":"6548"},{"category":"News _ Politics","count":"12","categoryId":"11","videoId":"6542"},{"category":"News _ Politics","count":"12","categoryId":"11","videoId":"6549"},{"category":"News _ Politics","count":"12","categoryId":"11","videoId":"6571"},{"category":"News _ Politics","count":"12","categoryId":"11","videoId":"6569"},{"category":"News _ Politics","count":"12","categoryId":"11","videoId":"6546"},{"category":"News _ Politics","count":"12","categoryId":"11","videoId":"6568"},{"category":"News _ Politics","count":"12","categoryId":"11","videoId":"6544"},{"category":"News _ Politics","count":"12","categoryId":"11","videoId":"6567"},{"category":"News _ Politics","count":"12","categoryId":"11","videoId":"6547"},{"category":"Travel _ Events","count":"10","categoryId":"6","videoId":"1553"},{"category":"Travel _ Events","count":"10","categoryId":"6","videoId":"1556"},{"category":"Travel _ Events","count":"10","categoryId":"6","videoId":"2100"},{"category":"Travel _ Events","count":"10","categoryId":"6","videoId":"2103"},{"category":"Travel _ Events","count":"10","categoryId":"6","videoId":"1554"},{"category":"Travel _ Events","count":"10","categoryId":"6","videoId":"1558"},{"category":"Travel _ Events","count":"10","categoryId":"6","videoId":"1557"},{"category":"Travel _ Events","count":"10","categoryId":"6","videoId":"2101"},{"category":"Travel _ Events","count":"10","categoryId":"6","videoId":"2102"},{"category":"Entertainment (Yes)","count":"12","categoryId":"10","videoId":"6621"},{"category":"Entertainment (Yes)","count":"12","categoryId":"10","videoId":"6618"},{"category":"Entertainment (Yes)","count":"12","categoryId":"10","videoId":"6617"},{"category":"Entertainment (Yes)","count":"12","categoryId":"10","videoId":"6623"},{"category":"Entertainment (Yes)","count":"12","categoryId":"10","videoId":"6626"},{"category":"Entertainment (Yes)","count":"12","categoryId":"10","videoId":"6625"},{"category":"Entertainment (Yes)","count":"12","categoryId":"10","videoId":"6622"},{"category":"Entertainment (Yes)","count":"12","categoryId":"10","videoId":"6627"},{"category":"Entertainment (Yes)","count":"12","categoryId":"10","videoId":"6619"},{"category":"Entertainment (Yes)","count":"12","categoryId":"10","videoId":"6624"},{"category":"Entertainment (Yes)","count":"12","categoryId":"10","videoId":"6620"},{"category":"Entertainment (Yes)","count":"12","categoryId":"10","videoId":"6628"},{"category":"Nonprofits _ Activism","count":"11","categoryId":"15","videoId":"6515"},{"category":"Nonprofits _ Activism","count":"11","categoryId":"15","videoId":"6514"},{"category":"Nonprofits _ Activism","count":"11","categoryId":"15","videoId":"6517"},{"category":"Nonprofits _ Activism","count":"11","categoryId":"15","videoId":"6521"},{"category":"Nonprofits _ Activism","count":"11","categoryId":"15","videoId":"6520"},{"category":"Nonprofits _ Activism","count":"11","categoryId":"15","videoId":"6523"},{"category":"Nonprofits _ Activism","count":"11","categoryId":"15","videoId":"6522"},{"category":"Nonprofits _ Activism","count":"11","categoryId":"15","videoId":"6519"},{"category":"Nonprofits _ Activism","count":"11","categoryId":"15","videoId":"6513"},{"category":"Nonprofits _ Activism","count":"11","categoryId":"15","videoId":"6518"},{"category":"Nonprofits _ Activism","count":"11","categoryId":"15","videoId":"6516"},{"category":"Gaming (Yes)","count":"12","categoryId":"7","videoId":"2120"},{"category":"Gaming (Yes)","count":"12","categoryId":"7","videoId":"2125"},{"category":"Gaming (Yes)","count":"12","categoryId":"7","videoId":"2115"},{"category":"Gaming (Yes)","count":"12","categoryId":"7","videoId":"2108"},{"category":"Gaming (Yes)","count":"12","categoryId":"7","videoId":"2137"},{"category":"Gaming (Yes)","count":"12","categoryId":"7","videoId":"2113"},{"category":"Gaming (Yes)","count":"12","categoryId":"7","videoId":"1996"},{"category":"Gaming (Yes)","count":"12","categoryId":"7","videoId":"1992"},{"category":"Gaming (Yes)","count":"12","categoryId":"7","videoId":"2150"},{"category":"Gaming (Yes)","count":"12","categoryId":"7","videoId":"2145"},{"category":"Gaming (Yes)","count":"12","categoryId":"7","videoId":"2118"},{"category":"Gaming (Yes)","count":"12","categoryId":"7","videoId":"2142"},{"category":"Film _ Animation (Yes)","count":"12","categoryId":"1","videoId":"305"},{"category":"Film _ Animation (Yes)","count":"12","categoryId":"1","videoId":"109"},{"category":"Film _ Animation (Yes)","count":"12","categoryId":"1","videoId":"117"},{"category":"Film _ Animation (Yes)","count":"12","categoryId":"1","videoId":"113"},{"category":"Film _ Animation (Yes)","count":"12","categoryId":"1","videoId":"798"},{"category":"Film _ Animation (Yes)","count":"12","categoryId":"1","videoId":"788"},{"category":"Film _ Animation (Yes)","count":"12","categoryId":"1","videoId":"352"},{"category":"Film _ Animation (Yes)","count":"12","categoryId":"1","videoId":"3"},{"category":"Film _ Animation (Yes)","count":"12","categoryId":"1","videoId":"796"},{"category":"Film _ Animation (Yes)","count":"12","categoryId":"1","videoId":"115"},{"category":"Film _ Animation (Yes)","count":"12","categoryId":"1","videoId":"114"},{"category":"Film _ Animation (Yes)","count":"12","categoryId":"1","videoId":"790"},{"category":"Autos _ Vehicles","count":"12","categoryId":"2","videoId":"6539"},{"category":"Autos _ Vehicles","count":"12","categoryId":"2","videoId":"6537"},{"category":"Autos _ Vehicles","count":"12","categoryId":"2","videoId":"6540"},{"category":"Autos _ Vehicles","count":"12","categoryId":"2","videoId":"6538"},{"category":"Autos _ Vehicles","count":"12","categoryId":"2","videoId":"6572"},{"category":"Autos _ Vehicles","count":"12","categoryId":"2","videoId":"6533"},{"category":"Autos _ Vehicles","count":"12","categoryId":"2","videoId":"6536"},{"category":"Autos _ Vehicles","count":"12","categoryId":"2","videoId":"6532"},{"category":"Autos _ Vehicles","count":"12","categoryId":"2","videoId":"6534"},{"category":"Autos _ Vehicles","count":"12","categoryId":"2","videoId":"6541"},{"category":"Autos _ Vehicles","count":"12","categoryId":"2","videoId":"6531"},{"category":"Autos _ Vehicles","count":"12","categoryId":"2","videoId":"6535"},{"category":"Sports (Yes)","count":"12","categoryId":"5","videoId":"6525"},{"category":"Sports (Yes)","count":"12","categoryId":"5","videoId":"6527"},{"category":"Sports (Yes)","count":"12","categoryId":"5","videoId":"792"},{"category":"Sports (Yes)","count":"12","categoryId":"5","videoId":"6528"},{"category":"Sports (Yes)","count":"12","categoryId":"5","videoId":"6562"},{"category":"Sports (Yes)","count":"12","categoryId":"5","videoId":"6529"},{"category":"Sports (Yes)","count":"12","categoryId":"5","videoId":"241"},{"category":"Sports (Yes)","count":"12","categoryId":"5","videoId":"254"},{"category":"Sports (Yes)","count":"12","categoryId":"5","videoId":"6524"},{"category":"Sports (Yes)","count":"12","categoryId":"5","videoId":"6530"},{"category":"Sports (Yes)","count":"12","categoryId":"5","videoId":"6526"},{"category":"Sports (Yes)","count":"12","categoryId":"5","videoId":"240"},{"category":"Comedy","count":"12","categoryId":"9","videoId":"6667"},{"category":"Comedy","count":"12","categoryId":"9","videoId":"6670"},{"category":"Comedy","count":"12","categoryId":"9","videoId":"6668"},{"category":"Comedy","count":"12","categoryId":"9","videoId":"6666"},{"category":"Comedy","count":"12","categoryId":"9","videoId":"6662"},{"category":"Comedy","count":"12","categoryId":"9","videoId":"6663"},{"category":"Comedy","count":"12","categoryId":"9","videoId":"6671"},{"category":"Comedy","count":"12","categoryId":"9","videoId":"6664"},{"category":"Comedy","count":"12","categoryId":"9","videoId":"6672"},{"category":"Comedy","count":"12","categoryId":"9","videoId":"6661"},{"category":"Comedy","count":"12","categoryId":"9","videoId":"6665"},{"category":"Comedy","count":"12","categoryId":"9","videoId":"6669"},{"category":"Pets _ Animals","count":"10","categoryId":"4","videoId":"6647"},{"category":"Pets _ Animals","count":"10","categoryId":"4","videoId":"544"},{"category":"Pets _ Animals","count":"10","categoryId":"4","videoId":"543"},{"category":"Pets _ Animals","count":"10","categoryId":"4","videoId":"1675"},{"category":"Pets _ Animals","count":"10","categoryId":"4","videoId":"489"},{"category":"Pets _ Animals","count":"10","categoryId":"4","videoId":"6641"},{"category":"Pets _ Animals","count":"10","categoryId":"4","videoId":"6643"},{"category":"Pets _ Animals","count":"10","categoryId":"4","videoId":"537"},{"category":"Pets _ Animals","count":"10","categoryId":"4","videoId":"248"},{"category":"Pets _ Animals","count":"10","categoryId":"4","videoId":"6640"},{"category":"Education","count":"12","categoryId":"13","videoId":"2159"},{"category":"Education","count":"12","categoryId":"13","videoId":"6635"},{"category":"Education","count":"12","categoryId":"13","videoId":"6636"},{"category":"Education","count":"12","categoryId":"13","videoId":"6634"},{"category":"Education","count":"12","categoryId":"13","videoId":"6633"},{"category":"Education","count":"12","categoryId":"13","videoId":"6632"},{"category":"Education","count":"12","categoryId":"13","videoId":"6629"},{"category":"Education","count":"12","categoryId":"13","videoId":"6637"},{"category":"Education","count":"12","categoryId":"13","videoId":"6638"},{"category":"Education","count":"12","categoryId":"13","videoId":"6639"},{"category":"Education","count":"12","categoryId":"13","videoId":"6631"},{"category":"Education","count":"12","categoryId":"13","videoId":"6630"},{"category":"Science _ Technology","count":"12","categoryId":"14","videoId":"1093"},{"category":"Science _ Technology","count":"12","categoryId":"14","videoId":"6576"},{"category":"Science _ Technology","count":"12","categoryId":"14","videoId":"340"},{"category":"Science _ Technology","count":"12","categoryId":"14","videoId":"6575"},{"category":"Science _ Technology","count":"12","categoryId":"14","videoId":"6577"},{"category":"Science _ Technology","count":"12","categoryId":"14","videoId":"310"},{"category":"Science _ Technology","count":"12","categoryId":"14","videoId":"6573"},{"category":"Science _ Technology","count":"12","categoryId":"14","videoId":"6579"},{"category":"Science _ Technology","count":"12","categoryId":"14","videoId":"6580"},{"category":"Science _ Technology","count":"12","categoryId":"14","videoId":"329"},{"category":"Science _ Technology","count":"12","categoryId":"14","videoId":"6581"},{"category":"Science _ Technology","count":"12","categoryId":"14","videoId":"6574"},{"category":"Music","count":"12","categoryId":"3","videoId":"6587"},{"category":"Music","count":"12","categoryId":"3","videoId":"6590"},{"category":"Music","count":"12","categoryId":"3","videoId":"11"},{"category":"Music","count":"12","categoryId":"3","videoId":"6593"},{"category":"Music","count":"12","categoryId":"3","videoId":"6584"},{"category":"Music","count":"12","categoryId":"3","videoId":"6586"},{"category":"Music","count":"12","categoryId":"3","videoId":"6592"},{"category":"Music","count":"12","categoryId":"3","videoId":"6589"},{"category":"Music","count":"12","categoryId":"3","videoId":"6583"},{"category":"Music","count":"12","categoryId":"3","videoId":"6582"},{"category":"Music","count":"12","categoryId":"3","videoId":"6591"},{"category":"Music","count":"12","categoryId":"3","videoId":"6588"},{"category":"Howto _ Style","count":"11","categoryId":"12","videoId":"2135"},{"category":"Howto _ Style","count":"11","categoryId":"12","videoId":"2045"},{"category":"Howto _ Style","count":"11","categoryId":"12","videoId":"2068"},{"category":"Howto _ Style","count":"11","categoryId":"12","videoId":"2053"},{"category":"Howto _ Style","count":"11","categoryId":"12","videoId":"2066"},{"category":"Howto _ Style","count":"11","categoryId":"12","videoId":"777"},{"category":"Howto _ Style","count":"11","categoryId":"12","videoId":"674"},{"category":"Howto _ Style","count":"11","categoryId":"12","videoId":"676"},{"category":"Howto _ Style","count":"11","categoryId":"12","videoId":"2067"},{"category":"Howto _ Style","count":"11","categoryId":"12","videoId":"786"},{"category":"Howto _ Style","count":"11","categoryId":"12","videoId":"2046"}]